README.md
setup.cfg
setup.py
pynterest_rate/__init__.py
pynterest_rate/base_interest_rate.py
pynterest_rate/compound_interest.py
pynterest_rate.egg-info/PKG-INFO
pynterest_rate.egg-info/SOURCES.txt
pynterest_rate.egg-info/dependency_links.txt
pynterest_rate.egg-info/not-zip-safe
pynterest_rate.egg-info/top_level.txt