Metadata-Version: 1.0
Name: pynterest-rate
Version: 0.0.0.dev1
Summary: Calculate future value
Home-page: UNKNOWN
Author: UNKNOWN
Author-email: UNKNOWN
License: UNKNOWN
Platform: UNKNOWN
